hebg/__init__.py
hebg/behavior.py
hebg/codegen.py
hebg/draw.py
hebg/graph.py
hebg/heb_graph.py
hebg/node.py
hebg/requirements_graph.py
hebg/unrolling.py
hebg/layouts/__init__.py
hebg/layouts/deterministic.py
hebg/layouts/metabased.py
hebg/layouts/metaheuristics.py
hebg/metrics/__init__.py
hebg/metrics/histograms.py
hebg/metrics/complexity/__init__.py
hebg/metrics/complexity/complexities.py
hebg/metrics/complexity/utils.py
hebg/metrics/utility/__init__.py
hebg/metrics/utility/binary_utility.py
hebg-0.2.4.dist-info/LICENSE
hebg-0.2.4.dist-info/METADATA
hebg-0.2.4.dist-info/WHEEL
hebg-0.2.4.dist-info/top_level.txt
hebg-0.2.4.dist-info/RECORD
